blockchair/__init__.py
blockchair/api.py
blockchair/exceptions.py
blockchair/utils.py
blockchair-1.0.9.dist-info/LICENSE
blockchair-1.0.9.dist-info/METADATA
blockchair-1.0.9.dist-info/WHEEL
blockchair-1.0.9.dist-info/top_level.txt
blockchair-1.0.9.dist-info/RECORD
